README.rst
setup.py
proxy2808/__init__.py
proxy2808/proxy2808.py
proxy2808/test.py
proxy2808.egg-info/PKG-INFO
proxy2808.egg-info/SOURCES.txt
proxy2808.egg-info/dependency_links.txt
proxy2808.egg-info/requires.txt
proxy2808.egg-info/top_level.txt