Metadata-Version: 1.2
Name: proxy2808
Version: 0.0.3
Summary: 2808 http/socks5 proxy
Home-page: https://www.2808proxy.com
Author: huang dao xu
Author-email: 382619605@qq.com
Maintainer: huang dao xu
Maintainer-email: 382619605@qq.com
License: BSD License
Platform: all
Classifier: Programming Language :: Python :: 3.5
Classifier: Programming Language :: Python :: 3.6
